README.md
setup.py
jumbo_api/__init__.py
jumbo_api/jumbo_api.py
jumbo_api/test_jumbo_api.py
jumbo_api/objects/__init__.py
jumbo_api/objects/basket.py
jumbo_api/objects/delivery.py
jumbo_api/objects/pick_up.py
jumbo_api/objects/price.py
jumbo_api/objects/profile.py
jumbo_api/objects/store.py
jumbo_api/objects/time_slot.py
python_jumbo_api.egg-info/PKG-INFO
python_jumbo_api.egg-info/SOURCES.txt
python_jumbo_api.egg-info/dependency_links.txt
python_jumbo_api.egg-info/requires.txt
python_jumbo_api.egg-info/top_level.txt