Metadata-Version: 2.1
Name: python-jumbo-api
Version: 0.5.5
Summary: Unofficial python wrapper for the Jumbo.com API, a way to view your orders, time slots and basket information
Home-page: https://www.github.com/peternijssen/python-jumbo-api/
Author: Peter Nijssen
Author-email: peter@peternijssen.nl
License: MIT
Platform: UNKNOWN
Classifier: Programming Language :: Python :: 3
Classifier: License :: OSI Approved :: MIT License
Classifier: Operating System :: OS Independent
